settrade/__init__.py
settrade/config.py
settrade/context.py
settrade/derivatives.py
settrade/equity.py
settrade/errors.py
settrade/market.py
settrade/realtime.py
settrade/user.py
settrade/util.py
settrade/pb/__init__.py
settrade/pb/bidofferv3_pb2.py
settrade/pb/candlestick_pb2.py
settrade/pb/exchinfodvv3_pb2.py
settrade/pb/exchinfoeqv3_pb2.py
settrade/pb/infoV3_pb2.py
settrade/pb/orderdvv3_pb2.py
settrade/pb/ordereqv3_pb2.py
settrade/pb/google/__init__.py
settrade/pb/google/type.py
tests/__init__.py
tests/conftest.py
tests/test_context.py
tests/test_derivatives_inv.py
tests/test_derivatives_inv_auto_queue.py
tests/test_derivatives_mkt.py
tests/test_equity.py
tests/test_market.py
tests/test_rate_limit.py
tests/test_refresh_token.py
tests/test_subscriber.py
tests/utils.py
jamesukae-0.0.1.dist-info/METADATA
jamesukae-0.0.1.dist-info/WHEEL
jamesukae-0.0.1.dist-info/top_level.txt
jamesukae-0.0.1.dist-info/RECORD
