Metadata-Version: 2.1
Name: jamesukae
Version: 0.0.1
Requires-Python: >=3.8.0
Requires-Dist: requests (>=2.27)
Requires-Dist: cryptography (>=37.0)
Requires-Dist: betterproto (>=1.2)
Requires-Dist: paho-mqtt (>=1.6)
Requires-Dist: ntplib (>=0.4)
